{
  "project_info": {
    "project_number": "548921778996",
    "firebase_url": "https://daftar-belanja-f2894.firebaseio.com",
    "project_id": "daftar-belanja-f2894",
    "storage_bucket": "daftar-belanja-f2894.appspot.com"
  },
  "client": [
    {
      "client_info": {
        "mobilesdk_app_id": "1:548921778996:android:2353a19d28025ba88e7b61",
        "android_client_info": {
          "package_name": "anis.nat.daftarbelanja"
        }
      },
      "oauth_client": [
        {
          "client_id": "548921778996-8fi9oeecu3hkfn6pea6nkq7d6h0bem4a.apps.googleusercontent.com",
          "client_type": 3
        }
      ],
      "api_key": [
        {
          "current_key": "AIzaSyD7mdiUggmllSmn0iZBpuqNrabeHNTUEwA"
        }
      ],
      "services": {
        "appinvite_service": {
          "other_platform_oauth_client": [
            {
              "client_id": "548921778996-8fi9oeecu3hkfn6pea6nkq7d6h0bem4a.apps.googleusercontent.com",
              "client_type": 3
            }
          ]
        }
      }
    }
  ],
  "configuration_version": "1"
}